<?xml version="1.0" encoding="utf-8"?>
<I c="RoleState" i="role_state" m="role.role_state" n="LN_RM:roleState_WalkbyTrader" s="12124699590721903827">
  <L n="_buffs">
    <U>
      <T n="buff_type">137592<!--buff_Role_Appropriateness_NoPlaying--></T>
    </U>
    <U>
      <T n="buff_type">130085<!--buff_Role_Appropriateness_Visitor--></T>
    </U>
    <U>
      <T n="buff_type">35390<!--Buff_Role_Appropriateness_NoSleeping--></T>
    </U>
    <U>
      <T n="buff_type">35372<!--Buff_Role_Appropriateness_NoEating--></T>
    </U>
    <U>
      <T n="buff_type">134457<!--buff_Role_Appropriateness_NoComputer--></T>
    </U>
    <U>
      <T n="buff_type">35368<!--Buff_Role_Appropriateness_NoBathing--></T>
    </U>
    <U>
      <T n="buff_type">35365<!--Buff_Role_Appropriateness_NoCooking--></T>
    </U>
    <U>
      <T n="buff_type">101052<!--Buff_Role_Appropriateness_NoCallToMeal--></T>
    </U>
    <U>
      <T n="buff_type">74343<!--buff_PreventRunning--></T>
    </U>
    <U>
      <T n="buff_type">35370<!--Buff_Role_Appropriateness_NoCleaning--></T>
    </U>
    <U>
      <T n="buff_type">108749<!--buff_Role_Appropriateness_NoTv--></T>
    </U>
    <U>
      <V t="disabled" n="buff_reason" />
      <T n="buff_type">108838<!--buff_Role_Appropriateness_NoReadBooks--></T>
    </U>
  </L>
  <L n="role_affordances">
    <T>17245757397107955764<!--LN_RM:social_Peasant_Sell--></T>
    <T>12711762121208404729<!--LN_RM:social_Peasant_Purchase--></T>
  </L>
  <U n="_off_lot_autonomy_buff">
    <T n="buff_type">38292<!--buff_offLotAutonomyMod_OnLotOnly--></T>
  </U>
  <L n="_portal_disallowance_tags">
    <E>PortalDisallowance_Ungreeted</E>
  </L>
</I>