<?xml version="1.0" encoding="utf-8"?>
<SimData version="0x00000101" u="0x00000000">
  <Instances>
    <I name="zoneModifierInfo_Convivial" schema="ZoneModifierDisplayInfo" type="Object">
      <T name="zone_modifier_description">0xD0F9AA89</T>
      <T name="zone_modifier_icon">2F7D0004-00000000-DA2F7A82B3949FE6</T>
      <T name="zone_modifier_name">0xD6DAC32D</T>
      <T name="zone_modifier_reference">12036173499665254732</T>
    </I>
  </Instances>
  <Schemas>
    <Schema name="ZoneModifierDisplayInfo" schema_hash="0x455D0D1F">
      <Columns>
        <Column name="zone_modifier_description" type="LocalizationKey" flags="0x00000000" />
        <Column name="zone_modifier_icon" type="ResourceKey" flags="0x00000000" />
        <Column name="zone_modifier_name" type="LocalizationKey" flags="0x00000000" />
        <Column name="zone_modifier_reference" type="TableSetReference" flags="0x00000000" />
      </Columns>
    </Schema>
  </Schemas>
</SimData>